tests/test_version.py
whttp/__init__.py
whttp/__main__.py
whttp/client.py
whttp/version.py
whttp-0.0.1.dist-info/LICENSE
whttp-0.0.1.dist-info/METADATA
whttp-0.0.1.dist-info/WHEEL
whttp-0.0.1.dist-info/entry_points.txt
whttp-0.0.1.dist-info/top_level.txt
whttp-0.0.1.dist-info/RECORD
