Metadata-Version: 2.1
Name: whttp
Version: 0.0.1
Summary: Create the skeleton for a python package/project
Home-page: https://github.com/joaompinto/whttp
Author: João Pinto
Author-email: lamego.pinto@gmail.com
License: MIT
Platform: UNKNOWN
License-File: LICENSE
Requires-Dist: pywin32
